Hack4u/__init__.py
Hack4u/courses.py
Hack4u/utils.py
test1_H4upackage-6.6.6.dist-info/METADATA
test1_H4upackage-6.6.6.dist-info/WHEEL
test1_H4upackage-6.6.6.dist-info/top_level.txt
test1_H4upackage-6.6.6.dist-info/RECORD
