Metadata-Version: 2.1
Name: test1_H4upackage
Version: 6.6.6
Summary: A test of project uploading (Hack4u courses)
Home-page: https://hack4u.io
Author: Luis González
